cgmzscore/__init__.py
cgmzscore/src/__init__.py
cgmzscore/src/calculate.py
cgmzscore/src/constant.py
cgmzscore/src/extract_value.py
cgmzscore/src/main.py
cgmzscore/src/table.py
cgmzscore/tables/lhfa_boys_0_5_zscores.json
cgmzscore/tables/lhfa_girls_0_5_zscores.json
cgmzscore/tables/wfa_boys_0_5_zscores.json
cgmzscore/tables/wfa_girls_0_5_zscores.json
cgmzscore/tables/wfh_boys_0_5_zscores.json
cgmzscore/tables/wfh_boys_2_5_zscores.json
cgmzscore/tables/wfh_girls_0_5_zscores.json
cgmzscore/tables/wfh_girls_2_5_zscores.json
cgmzscore/tables/wfl_boys_0_2_zscores.json
cgmzscore/tables/wfl_girls_0_2_zscores.json
cgmzscore-3.3.0.dist-info/METADATA
cgmzscore-3.3.0.dist-info/WHEEL
cgmzscore-3.3.0.dist-info/top_level.txt
cgmzscore-3.3.0.dist-info/RECORD
