Metadata-Version: 2.1
Name: cgmzscore
Version: 3.3.0
Summary: z-scores of anthropometric measurements of children below 5 years  based on WHO
Home-page: UNKNOWN
Author: Prajwal Kumar Singh
Author-email: prajwalsingh651@gmail.com
License: GPL
Platform: UNKNOWN
Classifier: Intended Audience :: Healthcare Industry
Classifier: Programming Language :: Python
Classifier: Programming Language :: Python :: 2.7
Classifier: Programming Language :: Python :: 3
Classifier: License :: OSI Approved :: GNU General Public License v3 or later (GPLv3+)
Classifier: Topic :: Scientific/Engineering :: Bio-Informatics
Classifier: Operating System :: OS Independent
